<?xml version="1.0" encoding="UTF-8" standalone="yes"?>
<serviceType id="IoApAsyncMessage" kind="business" longname="异步消息服务" package="cn.sunline.ltts.amsg.service" xsi:noNamespaceSchemaLocation="ltts-model.xsd" xmlns:xsi="http://www.w3.org/2001/XMLSchema-instance">
    <service id="publish" name="publish" longname="消息发布服务">
        <interface>
            <input packMode="false">
                <field id="mtinfo" type="TrxBaseEnvs.MessageTotalInfo" required="false" multi="false" array="false" longname="消息信息"/>
            </input>
            <output asParm="true" packMode="false"/>
            <property packMode="false"/>
            <printer packMode="false"/>
        </interface>
    </service>
    <service id="publishMri" name="publishMri" longname="消息发布服务MRI">
        <interface>
            <input packMode="false">
                <field id="mrinfo" type="TrxBaseEnvs.MessageRealInfo" required="false" multi="false" array="false" longname="消息信息"/>
            </input>
            <output asParm="true" packMode="false"/>
            <property packMode="false"/>
            <printer packMode="false"/>
        </interface>
    </service>
    <service id="sendMessage" name="sendMessage" longname="短信服务">
        <interface>
            <input packMode="false">
                <field id="mtinfo" type="TrxBaseEnvs.MessageTotalInfo" required="false" multi="false" array="false" longname="消息信息"/>
            </input>
            <output asParm="true" packMode="false"/>
            <property packMode="false"/>
            <printer packMode="true"/>
        </interface>
    </service>
    <service id="sendSMS" name="sendSMS" longname="直发短信服务">
        <interface>
            <input packMode="false">
                <field id="sms" type="ApMessageComplexType.SMSCType" required="false" multi="false" array="false" longname="短信内容"/>
            </input>
            <output asParm="true" packMode="false"/>
            <property packMode="false"/>
            <printer packMode="true"/>
        </interface>
    </service>
    <service id="sendSMSes" name="sendSMSes" longname="直发多条短信服务">
        <interface>
            <input packMode="false">
                <field id="smses" type="ApMessageComplexType.SMSCType" required="false" multi="true" array="false" longname="短信内容"/>
            </input>
            <output asParm="true" packMode="false"/>
            <property packMode="false"/>
            <printer packMode="true"/>
        </interface>
    </service>
    <service id="saveMessage" name="saveMessage" longname="保存消息">
        <interface>
            <input packMode="false">
                <field id="info" type="TrxBaseEnvs.MessageTotalInfo" required="false" multi="false" array="false" longname="消息辅助信息"/>
            </input>
            <output asParm="true" packMode="false"/>
            <property packMode="false"/>
            <printer packMode="true"/>
        </interface>
    </service>
    <service id="saveMessSucc" name="saveMessSucc" longname="保存成功消息">
        <interface>
            <input packMode="false">
                <field id="info" type="TrxBaseEnvs.MessageTotalInfo" required="false" multi="false" array="false" longname="消息辅助信息"/>
            </input>
            <output asParm="true" packMode="false"/>
            <property packMode="false"/>
            <printer packMode="true"/>
        </interface>
    </service>
    <service id="afterBatchSendSMS" name="afterBatchSendSMS" longname="批量后处理发送短信">
        <interface>
            <input packMode="false"/>
            <output asParm="true" packMode="false"/>
            <property packMode="false"/>
            <printer packMode="true"/>
        </interface>
    </service>
</serviceType>
