<?xml version="1.0" encoding="UTF-8" standalone="yes"?>
<serviceType id="IoOdOrderQuerySevType" kind="business" longname="订单模块查询服务" package="cn.sunline.ltts.busi.iobus.servicetype.od" xsi:noNamespaceSchemaLocation="ltts-model.xsd" xmlns:xsi="http://www.w3.org/2001/XMLSchema-instance">
    <service id="IoOdQryOrder" name="ioOdQryOrder" longname="理财订单列表查询">
        <interface>
            <input packMode="true">
                <field id="trantp" type="PbEnumType2.E_TRANTP" required="false" multi="false" array="false" longname="交易类型" ref="OdDict.Order.trantp"/>
                <field id="stdate" type="BaseType2.U_DATE08" required="false" multi="false" array="false" longname="起始日期"/>
                <field id="endate" type="BaseType2.U_DATE08" required="false" multi="false" array="false" longname="截止日期"/>
                <field id="fntrst" type="OdEnumType.E_FNTRST" required="false" multi="false" array="false" longname="理财状态" ref="OdDict.Order.fntrst"/>
                <field id="puacno" type="BaseType2.U_ACCTNO" required="false" default="''" multi="false" array="false" longname="购买账号" ref="OdDict.Order.puacno"/>
            </input>
            <output asParm="true" packMode="true">
                <field id="odfoout" type="IoOrderFormsOut.OdfnsDetlTranInfolist" required="false" multi="true" array="false" longname="输出列表"/>
            </output>
            <property packMode="false"/>
            <printer packMode="false"/>
        </interface>
    </service>
    <service id="IoOdQryOrderDel" name="ioOdQryOrderDel" longname="订单详细信息查询">
        <interface>
            <input packMode="true">
                <field id="sprdid" type="OdBaseType.U_SPRDID" required="false" default="''" multi="false" array="false" longname="可售产品ID" ref="OdDict.Order.sprdid"/>
                <field id="sprdvr" type="OdBaseType.U_PRODVR" required="false" default="0" multi="false" array="false" longname="可售产品版本" ref="OdDict.Order.sprdvr"/>
                <field id="purcid" type="OdBaseType.U_CUSTID" required="false" default="''" multi="false" array="false" longname="购买人ID" ref="OdDict.Order.purcid"/>
                <field id="ordrno" type="OdBaseType.U_ORDRNO" required="false" default="''" multi="false" array="false" longname="订单编号" ref="OdDict.Order.ordrno"/>
            </input>
            <output asParm="true" packMode="true">
                <field id="oddeinfo" type="IoOrderFormsOut.OrderFormsDet" required="false" multi="false" array="false" longname="订单详细信息"/>
            </output>
            <property packMode="false"/>
            <printer packMode="false"/>
        </interface>
    </service>
    <service id="IoOdQryFinOrd" name="odQryFinOrd" longname="查询理财订单">
        <interface>
            <input packMode="true">
                <field id="puacno" type="BaseType2.U_ACCTNO" required="false" default="''" multi="false" array="false" longname="购买账号" ref="OdDict.Order.puacno"/>
                <field id="sprdid" type="OdBaseType.U_SPRDID" required="false" default="''" multi="false" array="false" longname="可售产品ID" ref="OdDict.Order.sprdid"/>
                <field id="fnflag" type="OdEnumType.E_FNFLAG" required="false" default="0" multi="false" array="false" longname="查询标识"/>
            </input>
            <output asParm="true" packMode="true">
                <field id="orderlist" type="IoOrderFormsOut.QrOrderInfo" required="false" multi="true" array="false" longname="可赎回份额"/>
            </output>
            <property packMode="false"/>
            <printer packMode="false"/>
        </interface>
    </service>
    <service id="IoOdQryFinOrdDet" name="OdQryFinOrdDet" longname="查询理财订单详细信息">
        <interface>
            <input packMode="true">
                <field id="ordrno" type="OdBaseType.U_ORDRNO" required="false" default="''" multi="false" array="false" longname="订单编号" ref="OdDict.Order.ordrno"/>
                <field id="puacno" type="BaseType2.U_ACCTNO" required="false" default="''" multi="false" array="false" longname="购买账号" ref="OdDict.Order.puacno"/>
                <field id="sprdid" type="OdBaseType.U_SPRDID" required="false" default="''" multi="false" array="false" longname="可售产品ID" ref="OdDict.Order.sprdid"/>
                <field id="sprdvr" type="OdBaseType.U_PRODVR" required="false" default="0" multi="false" array="false" longname="可售产品版本" ref="OdDict.Order.sprdvr"/>
            </input>
            <output asParm="true" packMode="true">
                <field id="sprdid" type="OdBaseType.U_SPRDID" required="false" multi="false" array="false" longname="可售产品ID" ref="OdDict.Order.sprdid"/>
                <field id="sprdna" type="BaseType2.U_CHAR80" required="false" multi="false" array="false" longname="可售产品名称" ref="OdDict.Order.sprdna"/>
                <field id="ordram" type="BaseType2.U_TRANAM" required="false" multi="false" array="false" longname="金额/份额" ref="OdDict.Order.ordram"/>
                <field id="transt" type="OdEnumType.E_FNTRST" required="false" multi="false" array="false" longname="理财状态"/>
                <field id="trantp" type="PbEnumType2.E_TRANTP" required="false" multi="false" array="false" longname="交易类型" ref="OdDict.Order.trantp"/>
                <field id="trandt" type="PbBaseType2.U_DATE08" required="false" multi="false" array="false" longname="交易日期"/>
                <field id="frzedt" type="BaseType2.U_DATE08" required="false" multi="false" array="false" longname="冻结日期" ref="OdDict.Order.frzedt"/>
                <field id="frzesq" type="BaseType2.U_SEQUNO" required="false" multi="false" array="false" longname="冻结流水号" ref="OdDict.Order.frzesq"/>
                <field id="ortmpl" type="OdBaseType.U_DATETM" required="false" multi="false" array="false" longname="订单生成时间"/>
                <field id="bktmpl" type="OdBaseType.U_DATETM" required="false" multi="false" array="false" longname="预约确认日期时间" ref="OdDict.Order.bktmpl"/>
                <field id="shtmpl" type="OdBaseType.U_DATETM" required="false" multi="false" array="false" longname="扣款时间" ref="OdDict.Order.shtmpl"/>
                <field id="rttmpl" type="OdBaseType.U_DATETM" required="false" multi="false" array="false" longname="回款时间" ref="OdDict.Order.rttmpl"/>
                <field id="undotm" type="OdBaseType.U_DATETM" required="false" multi="false" array="false" longname="撤销时间"/>
                <field id="backf1" type="BaseType2.U_CHAR40" required="false" multi="false" array="false" longname="预留字段1"/>
                <field id="backf2" type="BaseType2.U_CHAR40" required="false" multi="false" array="false" longname="预留字段2"/>
                <field id="backf3" type="BaseType2.U_CHAR40" required="false" multi="false" array="false" longname="预留字段3"/>
                <field id="backf4" type="BaseType2.U_CHAR40" required="false" multi="false" array="false" longname="预留字段4"/>
                <field id="backf5" type="BaseType2.U_CHAR40" required="false" multi="false" array="false" longname="预留字段5"/>
            </output>
            <property packMode="false"/>
            <printer packMode="false"/>
        </interface>
    </service>
    <service id="IoOdQrySelSubOrd" name="qrySelSubOrd" longname="查询(子)订单信息">
        <interface>
            <input packMode="true">
                <field id="bpqytp" type="OdEnumType.E_BPQYTP" required="false" multi="false" array="false" longname="可售产品查询项"/>
                <field id="dtqytx" type="BaseType2.U_CHAR40" required="false" default="''" multi="false" array="false" longname="可售产品查询条件"/>
                <field id="sprdvr" type="string" required="false" multi="false" array="false" longname="可售产品版本号"/>
                <field id="ordrst" type="PbEnumType2.E_MAORST" required="false" multi="false" array="false" longname="订单状态" ref="OdDict.Order.ordrst"/>
                <field id="basetp" type="OdEnumType.E_BASETP" required="false" multi="false" array="false" longname="基础产品查询项"/>
                <field id="basetj" type="BaseType2.U_CHAR40" required="false" default="''" multi="false" array="false" longname="基础产品查询条件"/>
                <field id="basevr" type="string" required="false" multi="false" array="false" longname="基础产品版本号"/>
                <field id="cordst" type="PbEnumType2.E_CHORST" required="false" multi="false" array="false" longname="子订单状态" ref="OdDict.Order.cordst"/>
                <field id="begndt" type="BaseType2.U_DATE08" required="false" multi="false" array="false" longname="起始日期"/>
                <field id="endddt" type="BaseType2.U_DATE08" required="false" multi="false" array="false" longname="终止日期"/>
                <field id="detltg" type="OdEnumType.E_DETLTG" required="false" multi="false" array="false" longname="详细标志"/>
            </input>
            <output asParm="true" packMode="true">
                <field id="list" type="IoOrderFormsOut.OrderSubOrdOut" required="false" multi="true" array="false" longname="子订单查询输出复合类型"/>
            </output>
            <property packMode="false"/>
            <printer packMode="false"/>
        </interface>
    </service>
    <service id="IoOdQrySelMinOrd" name="qrySelMinOrd" longname="查询(总)订单信息">
        <interface>
            <input packMode="true">
                <field id="bpqytp" type="OdEnumType.E_BPQYTP" required="false" multi="false" array="false" longname="查询项目"/>
                <field id="dtqytx" type="BaseType2.U_CHAR32" required="false" default="''" multi="false" array="false" longname="查询条件"/>
                <field id="sprdvr" type="string" required="false" multi="false" array="false" longname="可售产品版本"/>
                <field id="ordrst" type="PbEnumType2.E_MAORST" required="false" multi="false" array="false" longname="订单状态" ref="OdDict.Order.ordrst"/>
                <field id="begndt" type="BaseType2.U_DATE08" required="false" multi="false" array="false" longname="起始日期"/>
                <field id="endddt" type="BaseType2.U_DATE08" required="false" multi="false" array="false" longname="终止日期"/>
                <field id="sprdft" type="PbEnumType2.E_SPRDFT" required="false" multi="false" array="false" longname="可售产品大类"/>
                <field id="source" type="SlEnumType.E_XITONG" required="false" multi="false" array="false" longname="请求系统简称"/>
                <field id="pageno" type="BaseType2.U_INTEGE" required="false" default="0" multi="false" array="false" longname="页码"/>
                <field id="pagesize" type="BaseType2.U_INTEGE" required="false" default="0" multi="false" array="false" longname="页容量"/>
                <field id="ordrno" type="OdBaseType.U_ORDRNO" required="false" default="''" multi="false" array="false" longname="订单编号"/>
                <field id="cardno" type="OdBaseType.U_CARDNO" required="false" multi="false" array="false" longname="电子账号"/>
            </input>
            <output asParm="true" packMode="true">
                <field id="list" type="IoOrderFormsOut.OrderMainOrdOut" required="false" multi="true" array="false" longname="主订单查询输出复合类型"/>
            </output>
            <property packMode="false"/>
            <printer packMode="false"/>
        </interface>
    </service>
    <service id="IoOdQryErrorOrder" name="ioOdQryErrorOrder" longname="查询异常订单">
        <interface>
            <input packMode="true">
                <field id="qrerod" type="OdEnumType.E_QREROD" required="false" multi="false" array="false" longname="异常订单查询项"/>
                <field id="begndt" type="BaseType2.U_DATE08" required="false" multi="false" array="false" longname="起始日期"/>
                <field id="endddt" type="BaseType2.U_DATE08" required="false" multi="false" array="false" longname="终止日期"/>
            </input>
            <output asParm="true" packMode="true">
                <field id="list" type="IoOrderFormsOut.ErrorOdOut" required="false" multi="true" array="false" longname="异常订单查询"/>
            </output>
            <property packMode="false"/>
            <printer packMode="false"/>
        </interface>
    </service>
    <service id="IoOdQryErrorOrderNew" name="ioOdQryErrorOrderNew" longname="查询异常订单新">
        <interface>
            <input packMode="true">
                <field id="qrerod" type="OdEnumType.E_QREROD" required="false" multi="false" array="false" longname="异常订单查询项"/>
                <field id="begndt" type="BaseType2.U_DATE08" required="false" multi="false" array="false" longname="起始日期"/>
                <field id="endddt" type="BaseType2.U_DATE08" required="false" multi="false" array="false" longname="终止日期"/>
            </input>
            <output asParm="true" packMode="true">
                <field id="list" type="IoOrderFormsOut.ErrorOdOut" required="false" multi="true" array="false" longname="异常订单查询"/>
            </output>
            <property packMode="false"/>
            <printer packMode="false"/>
        </interface>
    </service>
    <service id="IoOdQryOrderToApp" name="IoOdQryOrderToApp" longname="为APP提供查询委托订单信息查询接口">
        <interface>
            <input packMode="true">
                <field id="purcid" type="OdBaseType.U_CUSTID" required="false" default="''" multi="false" array="false" longname="购买人ID"/>
                <field id="sprdft" type="OdEnumType.E_SPRDFT" required="false" multi="false" array="false" longname="产品大类"/>
                <field id="begndt" type="BaseType2.U_DATE08" required="false" multi="false" array="false" longname="起始日期"/>
                <field id="endddt" type="BaseType2.U_DATE08" required="false" multi="false" array="false" longname="终止日期"/>
                <field id="qrtype" type="OdEnumType.E_APODTP" required="false" multi="false" array="false" longname="查询类型"/>
                <field id="cardno" type="OdBaseType.U_CARDNO" required="false" multi="false" array="false" longname="电子账号"/>
            </input>
            <output asParm="true" packMode="true">
                <field id="list" type="IoOrderFormsOut.OrderMainOrdOut" required="false" multi="true" array="false" longname="主订单查询输出复合类型"/>
            </output>
            <property packMode="false"/>
            <printer packMode="true"/>
        </interface>
    </service>
    <service id="IoOdQryOrderAgreeList" name="IoOdQryOrderAgreeList" longname="查询订单中包含的协议信息">
        <interface>
            <input packMode="true">
                <field id="ordrno" type="OdBaseType.U_ORDRNO" required="false" default="''" multi="false" array="false" longname="业务流水即总订单编号"/>
                <field id="purcid" type="OdBaseType.U_CUSTID" required="false" default="''" multi="false" array="false" longname="购买人ID"/>
                <field id="xytype" type="OdEnumType.E_XYTYPE" required="false" multi="false" array="false" longname="协议类型"/>
            </input>
            <output asParm="true" packMode="true">
                <field id="info" type="IoOrderFormsOut.agreeNewsInfo" required="false" multi="true" array="false" longname="订单包含的协议信息复合类型"/>
            </output>
            <property packMode="false"/>
            <printer packMode="true"/>
        </interface>
    </service>
    <service id="IoOdQryOrderAgreePath" name="IoOdQryOrderAgreePath" longname="查询订单中的协议地址信息">
        <interface>
            <input packMode="true">
                <field id="applid" type="OdBaseType.U_ORDRNO" required="false" default="''" multi="false" array="false" longname="业务流水"/>
                <field id="purcid" type="OdBaseType.U_CUSTID" required="false" default="''" multi="false" array="false" longname="客户编号"/>
                <field id="xytype" type="OdEnumType.E_XYTYPE" required="false" default="''" multi="false" array="false" longname="协议类型"/>
            </input>
            <output asParm="false" packMode="false">
                <field id="info" type="IoOrderFormsOut.agreePathVo" required="false" multi="true" array="false" longname="查询订单协议地址信息复合类型"/>
            </output>
            <property packMode="false"/>
            <printer packMode="true"/>
        </interface>
    </service>
</serviceType>
