<?xml version="1.0" encoding="UTF-8" standalone="yes"?>
<schema id="HcEnumType" package="cn.sunline.ltts.busi.sys.type" longname="热点控制限制类型" classgen="normal" xsi:noNamespaceSchemaLocation="ltts-model.xsd" xmlns:xsi="http://www.w3.org/2001/XMLSchema-instance">
    <restrictionType id="E_HCMOLD" longname="控制类型" base="BaseType.U_CHAR02" maxLength="2" minLength="1">
        <enumeration id="XE" value="1" longname="限额"/>
        <enumeration id="YE" value="2" longname="余额"/>
        <enumeration id="FE" value="3" longname="份额"/>
    </restrictionType>
    <restrictionType id="E_HCTYPE" longname="热点类型" base="BaseType.U_CHAR02" maxLength="2" minLength="1">
        <enumeration id="DP" value="1" longname="存款户"/>
        <enumeration id="IN" value="2" longname="内部户"/>
        <enumeration id="CL" value="3" longname="额度"/>
    </restrictionType>
    <restrictionType id="E_CTRLWY" longname="控制方式" base="BaseType.U_CHAR01" maxLength="1" minLength="1">
        <enumeration id="DD" value="1" longname="单点额度"/>
        <enumeration id="FS" value="2" longname="分散额度"/>
    </restrictionType>
    <restrictionType id="E_HCSTAS" longname="热点状态" base="BaseType.U_CHAR01" maxLength="1" minLength="1">
        <enumeration id="ZC" value="1" longname="正常"/>
        <enumeration id="SX" value="2" longname="失效"/>
    </restrictionType>
    <restrictionType id="E_DEALSS" longname="占用状态" base="BaseType.U_CHAR01" maxLength="1" minLength="1">
        <enumeration id="TZ" value="1" longname="调整释放"/>
        <enumeration id="SF" value="2" longname="已释放"/>
        <enumeration id="ZY" value="3" longname="已占用"/>
        <enumeration id="CG" value="4" longname="已成功"/>
        <enumeration id="SB" value="5" longname="已失败"/>
    </restrictionType>
    <restrictionType id="E_NESTYN" longname="是否冲正" base="BaseType.U_CHAR01">
        <enumeration id="CZ" value="0" longname="冲正"/>
        <enumeration id="BCZ" value="1" longname="不冲正"/>
    </restrictionType>
    <restrictionType id="E_DETLSS" longname="明细状态" base="BaseType.U_CHAR01">
        <enumeration id="WCL" value="1" longname="未处理"/>
        <enumeration id="CLZ" value="2" longname="余额处理中"/>
        <enumeration id="YCL" value="3" longname="余额已处理"/>
        <enumeration id="QTZ" value="4" longname="其他处理中"/>
        <enumeration id="QTY" value="5" longname="其他已处理"/>
        <enumeration id="QCL" value="6" longname="全部已处理"/>
        <enumeration id="YESB" value="7" longname="更新余额失败"/>
        <enumeration id="MXSB" value="8" longname="更新明细失败"/>
    </restrictionType>
    <restrictionType id="E_SYNCST" longname="同步状态" base="string" maxLength="1" minLength="1">
        <enumeration id="PEND" value="0" longname="待同步"/>
        <enumeration id="WAIT" value="1" longname="同步中"/>
        <enumeration id="SUCC" value="2" longname="已同步"/>
    </restrictionType>
    <restrictionType id="E_HSREAD" longname="读取标志" base="string" maxLength="1" minLength="1">
        <enumeration id="WD" value="1" longname="未读"/>
        <enumeration id="YD" value="2" longname="已读"/>
    </restrictionType>
</schema>
